setup.py
lib/strider/__init__.py
lib/strider.egg-info/PKG-INFO
lib/strider.egg-info/SOURCES.txt
lib/strider.egg-info/dependency_links.txt
lib/strider.egg-info/requires.txt
lib/strider.egg-info/top_level.txt
lib/strider/common/__init__.py
lib/strider/common/commands.py
lib/strider/common/instance_data.py
lib/strider/common/logger.py
lib/strider/provisioners/__init__.py
lib/strider/provisioners/shell.py
lib/strider/utils/__init__.py
lib/strider/utils/commands.py
lib/strider/utils/instance_data.py
lib/strider/utils/logger.py
lib/strider/virt/__init__.py
lib/strider/virt/ec2.py
lib/strider/virt/vagrantbox.py