Metadata-Version: 1.0
Name: strider
Version: 0.0.12
Summary: Strider builds dev VMs and bakes cloud images.
Home-page: http://github.com/mpdehaan/strider/
Author: Michael DeHaan
Author-email: michael.dehaan@gmail.com
License: Apache2
Platform: UNKNOWN
